propfit/__init__.py
propfit/propfit.py
propfit/default databases/1st order groups.csv
propfit/default databases/2nd order groups.csv
propfit/default databases/default database.csv
propfit-1.1.5.dist-info/licenses/LICENSE
propfit-1.1.5.dist-info/METADATA
propfit-1.1.5.dist-info/WHEEL
propfit-1.1.5.dist-info/top_level.txt
propfit-1.1.5.dist-info/RECORD
